__init__.py
expression.py
myminixform.py
myminixform-1.0.8.dist-info/LICENSE.txt
myminixform-1.0.8.dist-info/METADATA
myminixform-1.0.8.dist-info/WHEEL
myminixform-1.0.8.dist-info/top_level.txt
myminixform-1.0.8.dist-info/RECORD
