Metadata-Version: 2.1
Name: myminixform
Version: 1.0.8
Summary: Un package python pour creer un formulaire XLSFORM à partir d'un fichier YAML
Author-email: La centrale cognitive <lacentrale.cognitive@gmail.com>, mr_kam <kanicetcyrille@gmail.com>
Maintainer-email: mr_kam <kanicetcyrille@gmail.com>, Al-Waris <dossigue04@gmail.com>
License: Copyright (c) 2018 The Python Packaging Authority
Project-URL: Homepage, https://github.com/Mr-KAM/myminixform
Project-URL: Documentation, https://github.com/Mr-KAM/myminixform
Project-URL: Repository, https://github.com/Mr-KAM/myminixform.git
Project-URL: Bug Tracker, https://github.com/Mr-KAM/myminixform/issues
Keywords: formulaire,XLSFORM,minixform,python,kobo,ODK
Classifier: Programming Language :: Python :: 3
Classifier: License :: OSI Approved :: MIT License
Classifier: Operating System :: OS Independent
Classifier: Topic :: Software Development :: Build Tools
Requires-Python: >=3.6
License-File: LICENSE.txt
Requires-Dist: pandas ==2.1.4
Requires-Dist: openpyxl ==3.1.2
Requires-Dist: humre ==1.0.0
Requires-Dist: PyYAML ==6.0.1
Requires-Dist: rich ==13.9.4
